lost_n_phoned-1.0.0.dist-info/METADATA
lost_n_phoned-1.0.0.dist-info/RECORD
lost_n_phoned-1.0.0.dist-info/WHEEL
lost_n_phoned-1.0.0.dist-info/top_level.txt
lostnphoned/__init__.py
lostnphoned/schema.sql
lostnphoned/sms.py
lostnphoned/sql.py
