Metadata-Version: 2.1
Name: lost-n-phoned
Version: 1.0.0
Summary: Get your contacts from a stranger's phone
Home-page: https://github.com/ljacob15/lost-and-phoned
Maintainer: Keane Nguyen
Maintainer-email: keanekyn@gmail.com
License: UNKNOWN
Platform: UNKNOWN
Requires-Python: >=3.4
Requires-Dist: flask
Requires-Dist: requests
Requires-Dist: google-auth
Requires-Dist: google-auth-oauthlib
Requires-Dist: google-auth-httplib2
Requires-Dist: google-api-python-client
Requires-Dist: twilio
Requires-Dist: phonenumberslite
Requires-Dist: schedule
